[
    {
        "dataVersion": 100,
        "versionName": "15w32a"
    },
    {
        "dataVersion": 103,
        "versionName": "15w32b"
    },
    {
        "dataVersion": 104,
        "versionName": "15w32c"
    },
    {
        "dataVersion": 111,
        "versionName": "15w33 (a or b)"
    },
    {
        "dataVersion": 112,
        "versionName": "15w33c"
    },
    {
        "dataVersion": 114,
        "versionName": "15w34a"
    },
    {
        "dataVersion": 115,
        "versionName": "15w34b"
    },
    {
        "dataVersion": 116,
        "versionName": "15w34c"
    },
    {
        "dataVersion": 117,
        "versionName": "15w34d"
    },
    {
        "dataVersion": 118,
        "versionName": "15w35a"
    },
    {
        "dataVersion": 119,
        "versionName": "15w35b"
    },
    {
        "dataVersion": 120,
        "versionName": "15w35c"
    },
    {
        "dataVersion": 121,
        "versionName": "15w35d"
    },
    {
        "dataVersion": 122,
        "versionName": "15w35e"
    },
    {
        "dataVersion": 123,
        "versionName": "15w36a"
    },
    {
        "dataVersion": 124,
        "versionName": "15w36b"
    },
    {
        "dataVersion": 125,
        "versionName": "15w36c"
    },
    {
        "dataVersion": 126,
        "versionName": "15w36d"
    },
    {
        "dataVersion": 127,
        "versionName": "15w37a"
    },
    {
        "dataVersion": 128,
        "versionName": "15w38a"
    },
    {
        "dataVersion": 129,
        "versionName": "15w38b"
    },
    {
        "dataVersion": 130,
        "versionName": "15w39a"
    },
    {
        "dataVersion": 131,
        "versionName": "15w39b"
    },
    {
        "dataVersion": 132,
        "versionName": "15w39c"
    },
    {
        "dataVersion": 133,
        "versionName": "15w40a"
    },
    {
        "dataVersion": 134,
        "versionName": "15w40b"
    },
    {
        "dataVersion": 136,
        "versionName": "15w41a"
    },
    {
        "dataVersion": 137,
        "versionName": "15w41b"
    },
    {
        "dataVersion": 138,
        "versionName": "15w42a"
    },
    {
        "dataVersion": 139,
        "versionName": "15w43a"
    },
    {
        "dataVersion": 140,
        "versionName": "15w43b"
    },
    {
        "dataVersion": 141,
        "versionName": "15w43c"
    },
    {
        "dataVersion": 142,
        "versionName": "15w44a"
    },
    {
        "dataVersion": 143,
        "versionName": "15w44b"
    },
    {
        "dataVersion": 145,
        "versionName": "15w45a"
    },
    {
        "dataVersion": 146,
        "versionName": "15w46a"
    },
    {
        "dataVersion": 148,
        "versionName": "15w47a"
    },
    {
        "dataVersion": 149,
        "versionName": "15w47b"
    },
    {
        "dataVersion": 150,
        "versionName": "15w47c"
    },
    {
        "dataVersion": 151,
        "versionName": "15w49a"
    },
    {
        "dataVersion": 152,
        "versionName": "15w49b"
    },
    {
        "dataVersion": 153,
        "versionName": "15w50a"
    },
    {
        "dataVersion": 154,
        "versionName": "15w51a"
    },
    {
        "dataVersion": 155,
        "versionName": "15w51b"
    },
    {
        "dataVersion": 156,
        "versionName": "16w02a"
    },
    {
        "dataVersion": 157,
        "versionName": "16w03a"
    },
    {
        "dataVersion": 158,
        "versionName": "16w04a"
    },
    {
        "dataVersion": 159,
        "versionName": "16w05a"
    },
    {
        "dataVersion": 160,
        "versionName": "16w05b"
    },
    {
        "dataVersion": 161,
        "versionName": "16w06a"
    },
    {
        "dataVersion": 162,
        "versionName": "16w07a"
    },
    {
        "dataVersion": 163,
        "versionName": "16w07b"
    },
    {
        "dataVersion": 164,
        "versionName": "1.9 Pre-release 1"
    },
    {
        "dataVersion": 165,
        "versionName": "1.9 Pre-release 2"
    },
    {
        "dataVersion": 167,
        "versionName": "1.9 Pre-release 3"
    },
    {
        "dataVersion": 168,
        "versionName": "1.9 Pre-release 4"
    },
    {
        "dataVersion": 169,
        "versionName": "1.9"
    },
    {
        "dataVersion": 170,
        "versionName": "1.9.1 Pre-release 1"
    },
    {
        "dataVersion": 171,
        "versionName": "1.9.1 Pre-release 2"
    },
    {
        "dataVersion": 172,
        "versionName": "1.9.1 Pre-release 3"
    },
    {
        "dataVersion": 175,
        "versionName": "1.9.1"
    },
    {
        "dataVersion": 176,
        "versionName": "1.9.2"
    },
    {
        "dataVersion": 177,
        "versionName": "16w14a"
    },
    {
        "dataVersion": 178,
        "versionName": "16w15a"
    },
    {
        "dataVersion": 179,
        "versionName": "16w15b"
    },
    {
        "dataVersion": 180,
        "versionName": "1.9.3 Pre-release 1"
    },
    {
        "dataVersion": 181,
        "versionName": "1.9.3 Pre-release 2"
    },
    {
        "dataVersion": 182,
        "versionName": "1.9.3 Pre-release 3"
    },
    {
        "dataVersion": 183,
        "versionName": "1.9.3"
    },
    {
        "dataVersion": 184,
        "versionName": "1.9.4"
    },
    {
        "dataVersion": 501,
        "versionName": "16w20a"
    },
    {
        "dataVersion": 503,
        "versionName": "16w21a"
    },
    {
        "dataVersion": 504,
        "versionName": "16w21b"
    },
    {
        "dataVersion": 506,
        "versionName": "1.10 Pre-release 1"
    },
    {
        "dataVersion": 507,
        "versionName": "1.10 Pre-release 2"
    },
    {
        "dataVersion": 510,
        "versionName": "1.10"
    },
    {
        "dataVersion": 511,
        "versionName": "1.10.1"
    },
    {
        "dataVersion": 512,
        "versionName": "1.10.2"
    },
    {
        "dataVersion": 800,
        "versionName": "16w32a"
    },
    {
        "dataVersion": 801,
        "versionName": "16w32b"
    },
    {
        "dataVersion": 802,
        "versionName": "16w33a"
    },
    {
        "dataVersion": 803,
        "versionName": "16w35a"
    },
    {
        "dataVersion": 805,
        "versionName": "16w36a"
    },
    {
        "dataVersion": 807,
        "versionName": "16w38a"
    },
    {
        "dataVersion": 809,
        "versionName": "16w39a"
    },
    {
        "dataVersion": 811,
        "versionName": "16w39b"
    },
    {
        "dataVersion": 812,
        "versionName": "16w39c"
    },
    {
        "dataVersion": 813,
        "versionName": "16w40a"
    },
    {
        "dataVersion": 814,
        "versionName": "16w41a"
    },
    {
        "dataVersion": 815,
        "versionName": "16w42a"
    },
    {
        "dataVersion": 816,
        "versionName": "16w43a"
    },
    {
        "dataVersion": 817,
        "versionName": "16w44a"
    },
    {
        "dataVersion": 818,
        "versionName": "1.11 Pre-release 1"
    },
    {
        "dataVersion": 819,
        "versionName": "1.11"
    },
    {
        "dataVersion": 920,
        "versionName": "16w50a"
    },
    {
        "dataVersion": 921,
        "versionName": "1.11.1"
    },
    {
        "dataVersion": 922,
        "versionName": "1.11.2"
    },
    {
        "dataVersion": 1022,
        "versionName": "17w06a"
    },
    {
        "dataVersion": 1122,
        "versionName": "17w13a"
    },
    {
        "dataVersion": 1123,
        "versionName": "17w13b"
    },
    {
        "dataVersion": 1124,
        "versionName": "17w14a"
    },
    {
        "dataVersion": 1125,
        "versionName": "17w15a"
    },
    {
        "dataVersion": 1126,
        "versionName": "17w16a"
    },
    {
        "dataVersion": 1127,
        "versionName": "17w16b"
    },
    {
        "dataVersion": 1128,
        "versionName": "17w17a"
    },
    {
        "dataVersion": 1129,
        "versionName": "17w17b"
    },
    {
        "dataVersion": 1130,
        "versionName": "17w18a"
    },
    {
        "dataVersion": 1131,
        "versionName": "17w18b"
    },
    {
        "dataVersion": 1132,
        "versionName": "1.12 Pre-release 1"
    },
    {
        "dataVersion": 1133,
        "versionName": "1.12 Pre-release 2"
    },
    {
        "dataVersion": 1134,
        "versionName": "1.12 Pre-release 3"
    },
    {
        "dataVersion": 1135,
        "versionName": "1.12 Pre-release 4"
    },
    {
        "dataVersion": 1136,
        "versionName": "1.12 Pre-release 5"
    },
    {
        "dataVersion": 1137,
        "versionName": "1.12 Pre-release 6"
    },
    {
        "dataVersion": 1138,
        "versionName": "1.12 Pre-release 7"
    },
    {
        "dataVersion": 1139,
        "versionName": "1.12"
    },
    {
        "dataVersion": 1239,
        "versionName": "17w31a"
    },
    {
        "dataVersion": 1240,
        "versionName": "1.12.1 Pre-release 1"
    },
    {
        "dataVersion": 1241,
        "versionName": "1.12.1"
    },
    {
        "dataVersion": 1341,
        "versionName": "1.12.2 Pre-release 1"
    },
    {
        "dataVersion": 1342,
        "versionName": "1.12.2 Pre-release 2"
    },
    {
        "dataVersion": 1343,
        "versionName": "1.12.2"
    },
    {
        "dataVersion": 1444,
        "versionName": "17w43a"
    },
    {
        "dataVersion": 1445,
        "versionName": "17w43b"
    },
    {
        "dataVersion": 1447,
        "versionName": "17w45a"
    },
    {
        "dataVersion": 1448,
        "versionName": "17w45b"
    },
    {
        "dataVersion": 1449,
        "versionName": "17w46a"
    },
    {
        "dataVersion": 1451,
        "versionName": "17w47a"
    },
    {
        "dataVersion": 1452,
        "versionName": "17w47b"
    },
    {
        "dataVersion": 1453,
        "versionName": "17w48a"
    },
    {
        "dataVersion": 1454,
        "versionName": "17w49a"
    },
    {
        "dataVersion": 1455,
        "versionName": "17w49b"
    },
    {
        "dataVersion": 1457,
        "versionName": "17w50a"
    },
    {
        "dataVersion": 1459,
        "versionName": "18w01a"
    },
    {
        "dataVersion": 1461,
        "versionName": "18w02a"
    },
    {
        "dataVersion": 1462,
        "versionName": "18w03a"
    },
    {
        "dataVersion": 1463,
        "versionName": "18w03b"
    },
    {
        "dataVersion": 1464,
        "versionName": "18w05a"
    },
    {
        "dataVersion": 1466,
        "versionName": "18w06a"
    },
    {
        "dataVersion": 1467,
        "versionName": "18w07a"
    },
    {
        "dataVersion": 1468,
        "versionName": "18w07b"
    },
    {
        "dataVersion": 1469,
        "versionName": "18w07c"
    },
    {
        "dataVersion": 1470,
        "versionName": "18w08a"
    },
    {
        "dataVersion": 1471,
        "versionName": "18w08b"
    },
    {
        "dataVersion": 1472,
        "versionName": "18w09a"
    },
    {
        "dataVersion": 1473,
        "versionName": "18w10a"
    },
    {
        "dataVersion": 1474,
        "versionName": "18w10b"
    },
    {
        "dataVersion": 1476,
        "versionName": "18w10c"
    },
    {
        "dataVersion": 1477,
        "versionName": "18w10d"
    },
    {
        "dataVersion": 1478,
        "versionName": "18w11a"
    },
    {
        "dataVersion": 1479,
        "versionName": "18w14a"
    },
    {
        "dataVersion": 1481,
        "versionName": "18w14b"
    },
    {
        "dataVersion": 1482,
        "versionName": "18w15a"
    },
    {
        "dataVersion": 1483,
        "versionName": "18w16a"
    },
    {
        "dataVersion": 1484,
        "versionName": "18w19a"
    },
    {
        "dataVersion": 1485,
        "versionName": "18w19b"
    },
    {
        "dataVersion": 1489,
        "versionName": "18w20a"
    },
    {
        "dataVersion": 1491,
        "versionName": "18w20b"
    },
    {
        "dataVersion": 1493,
        "versionName": "18w20c"
    },
    {
        "dataVersion": 1495,
        "versionName": "18w21a"
    },
    {
        "dataVersion": 1496,
        "versionName": "18w21b"
    },
    {
        "dataVersion": 1497,
        "versionName": "18w22a"
    },
    {
        "dataVersion": 1498,
        "versionName": "18w22b"
    },
    {
        "dataVersion": 1499,
        "versionName": "18w22c"
    },
    {
        "dataVersion": 1501,
        "versionName": "1.13 Pre-release 1"
    },
    {
        "dataVersion": 1502,
        "versionName": "1.13 Pre-release 2"
    },
    {
        "dataVersion": 1503,
        "versionName": "1.13 Pre-release 3"
    },
    {
        "dataVersion": 1504,
        "versionName": "1.13 Pre-release 4"
    },
    {
        "dataVersion": 1511,
        "versionName": "1.13 Pre-release 5"
    },
    {
        "dataVersion": 1512,
        "versionName": "1.13 Pre-release 6"
    },
    {
        "dataVersion": 1513,
        "versionName": "1.13 Pre-release 7"
    },
    {
        "dataVersion": 1516,
        "versionName": "1.13 Pre-release 8"
    },
    {
        "dataVersion": 1517,
        "versionName": "1.13 Pre-release 9"
    },
    {
        "dataVersion": 1518,
        "versionName": "1.13 Pre-release 10"
    },
    {
        "dataVersion": 1519,
        "versionName": "1.13"
    },
    {
        "dataVersion": 1620,
        "versionName": "18w30a"
    },
    {
        "dataVersion": 1621,
        "versionName": "18w30b"
    },
    {
        "dataVersion": 1622,
        "versionName": "18w31a"
    },
    {
        "dataVersion": 1623,
        "versionName": "18w32a"
    },
    {
        "dataVersion": 1625,
        "versionName": "18w33a"
    },
    {
        "dataVersion": 1626,
        "versionName": "1.13.1 Pre-release 1"
    },
    {
        "dataVersion": 1627,
        "versionName": "1.13.1 Pre-release 2"
    },
    {
        "dataVersion": 1628,
        "versionName": "1.13.1"
    },
    {
        "dataVersion": 1629,
        "versionName": "1.13.2 Pre-release 1"
    },
    {
        "dataVersion": 1630,
        "versionName": "1.13.2 Pre-release 2"
    },
    {
        "dataVersion": 1631,
        "versionName": "1.13.2"
    },
    {
        "dataVersion": 1901,
        "versionName": "18w43a"
    },
    {
        "dataVersion": 1902,
        "versionName": "18w43b"
    },
    {
        "dataVersion": 1903,
        "versionName": "18w43c"
    },
    {
        "dataVersion": 1907,
        "versionName": "18w44a"
    },
    {
        "dataVersion": 1908,
        "versionName": "18w45a"
    },
    {
        "dataVersion": 1910,
        "versionName": "18w46a"
    },
    {
        "dataVersion": 1912,
        "versionName": "18w47a"
    },
    {
        "dataVersion": 1913,
        "versionName": "18w47b"
    },
    {
        "dataVersion": 1914,
        "versionName": "18w48a"
    },
    {
        "dataVersion": 1915,
        "versionName": "18w48b"
    },
    {
        "dataVersion": 1916,
        "versionName": "18w49a"
    },
    {
        "dataVersion": 1919,
        "versionName": "18w50a"
    },
    {
        "dataVersion": 1921,
        "versionName": "19w02a"
    },
    {
        "dataVersion": 1922,
        "versionName": "19w03a"
    },
    {
        "dataVersion": 1923,
        "versionName": "19w03b"
    },
    {
        "dataVersion": 1924,
        "versionName": "19w03c"
    },
    {
        "dataVersion": 1926,
        "versionName": "19w04a"
    },
    {
        "dataVersion": 1927,
        "versionName": "19w04b"
    },
    {
        "dataVersion": 1930,
        "versionName": "19w05a"
    },
    {
        "dataVersion": 1931,
        "versionName": "19w06a"
    },
    {
        "dataVersion": 1932,
        "versionName": "19w07a"
    },
    {
        "dataVersion": 1933,
        "versionName": "19w08a"
    },
    {
        "dataVersion": 1934,
        "versionName": "19w08b"
    },
    {
        "dataVersion": 1935,
        "versionName": "19w09a"
    },
    {
        "dataVersion": 1937,
        "versionName": "19w11a"
    },
    {
        "dataVersion": 1938,
        "versionName": "19w11b"
    },
    {
        "dataVersion": 1940,
        "versionName": "19w12a"
    },
    {
        "dataVersion": 1941,
        "versionName": "19w12b"
    },
    {
        "dataVersion": 1942,
        "versionName": "19w13a"
    },
    {
        "dataVersion": 1943,
        "versionName": "19w13b"
    },
    {
        "dataVersion": 1944,
        "versionName": "19w14a"
    },
    {
        "dataVersion": 1945,
        "versionName": "19w14b"
    },
    {
        "dataVersion": 1947,
        "versionName": "1.14 Pre-release 1"
    },
    {
        "dataVersion": 1948,
        "versionName": "1.14 Pre-release 2"
    },
    {
        "dataVersion": 1949,
        "versionName": "1.14 Pre-release 3"
    },
    {
        "dataVersion": 1950,
        "versionName": "1.14 Pre-release 4"
    },
    {
        "dataVersion": 1951,
        "versionName": "1.14 Pre-release 5"
    },
    {
        "dataVersion": 1952,
        "versionName": "1.14"
    },
    {
        "dataVersion": 1955,
        "versionName": "1.14.1 Pre-release 1"
    },
    {
        "dataVersion": 1956,
        "versionName": "1.14.1 Pre-release 2"
    },
    {
        "dataVersion": 1957,
        "versionName": "1.14.1"
    },
    {
        "dataVersion": 1958,
        "versionName": "1.14.2 Pre-release 1"
    },
    {
        "dataVersion": 1959,
        "versionName": "1.14.2 Pre-release 2"
    },
    {
        "dataVersion": 1960,
        "versionName": "1.14.2 Pre-release 3"
    },
    {
        "dataVersion": 1962,
        "versionName": "1.14.2 Pre-release 4"
    },
    {
        "dataVersion": 1963,
        "versionName": "1.14.2"
    },
    {
        "dataVersion": 1964,
        "versionName": "1.14.3 Pre-release 1"
    },
    {
        "dataVersion": 1965,
        "versionName": "1.14.3 Pre-release 2"
    },
    {
        "dataVersion": 1966,
        "versionName": "1.14.3 Pre-release 3"
    },
    {
        "dataVersion": 1967,
        "versionName": "1.14.3 Pre-release 4"
    },
    {
        "dataVersion": 1968,
        "versionName": "1.14.3"
    },
    {
        "dataVersion": 1969,
        "versionName": "1.14.4 Pre-release 1"
    },
    {
        "dataVersion": 1970,
        "versionName": "1.14.4 Pre-release 2"
    },
    {
        "dataVersion": 1971,
        "versionName": "1.14.4 Pre-release 3"
    },
    {
        "dataVersion": 1972,
        "versionName": "1.14.4 Pre-release 4"
    },
    {
        "dataVersion": 1973,
        "versionName": "1.14.4 Pre-release 5"
    },
    {
        "dataVersion": 1974,
        "versionName": "1.14.4 Pre-release 6"
    },
    {
        "dataVersion": 1975,
        "versionName": "1.14.4 Pre-release 7"
    },
    {
        "dataVersion": 1976,
        "versionName": "1.14.4"
    },
    {
        "dataVersion": 2067,
        "versionName": "1.14.3 - Combat Test"
    },
    {
        "dataVersion": 2068,
        "versionName": "Combat Test 2"
    },
    {
        "dataVersion": 2069,
        "versionName": "Combat Test 3"
    },
    {
        "dataVersion": 2200,
        "versionName": "19w34a"
    },
    {
        "dataVersion": 2201,
        "versionName": "19w35a"
    },
    {
        "dataVersion": 2203,
        "versionName": "19w36a"
    },
    {
        "dataVersion": 2204,
        "versionName": "19w37a"
    },
    {
        "dataVersion": 2205,
        "versionName": "19w38a"
    },
    {
        "dataVersion": 2206,
        "versionName": "19w38b"
    },
    {
        "dataVersion": 2207,
        "versionName": "19w39a"
    },
    {
        "dataVersion": 2208,
        "versionName": "19w40a"
    },
    {
        "dataVersion": 2210,
        "versionName": "19w41a"
    },
    {
        "dataVersion": 2212,
        "versionName": "19w42a"
    },
    {
        "dataVersion": 2213,
        "versionName": "19w44a"
    },
    {
        "dataVersion": 2214,
        "versionName": "19w45a"
    },
    {
        "dataVersion": 2215,
        "versionName": "19w45b"
    },
    {
        "dataVersion": 2216,
        "versionName": "19w46a"
    },
    {
        "dataVersion": 2217,
        "versionName": "19w46b"
    },
    {
        "dataVersion": 2218,
        "versionName": "1.15 Pre-release 1"
    },
    {
        "dataVersion": 2219,
        "versionName": "1.15 Pre-release 2"
    },
    {
        "dataVersion": 2220,
        "versionName": "1.15 Pre-release 3"
    },
    {
        "dataVersion": 2221,
        "versionName": "1.15 Pre-release 4"
    },
    {
        "dataVersion": 2222,
        "versionName": "1.15 Pre-release 5"
    },
    {
        "dataVersion": 2223,
        "versionName": "1.15 Pre-release 6"
    },
    {
        "dataVersion": 2224,
        "versionName": "1.15 Pre-release 7"
    },
    {
        "dataVersion": 2225,
        "versionName": "1.15"
    },
    {
        "dataVersion": 2226,
        "versionName": "1.15.1 Pre-release 1"
    },
    {
        "dataVersion": 2227,
        "versionName": "1.15.1"
    },
    {
        "dataVersion": 2228,
        "versionName": "1.15.2 Pre-release 1"
    },
    {
        "dataVersion": 2229,
        "versionName": "1.15.2 Pre-release 2"
    },
    {
        "dataVersion": 2230,
        "versionName": "1.15.2"
    },
    {
        "dataVersion": 2320,
        "versionName": "Combat Test 4"
    },
    {
        "dataVersion": 2321,
        "versionName": "Combat Test 5"
    },
    {
        "dataVersion": 2504,
        "versionName": "20w06a"
    },
    {
        "dataVersion": 2506,
        "versionName": "20w07a"
    },
    {
        "dataVersion": 2507,
        "versionName": "20w08a"
    },
    {
        "dataVersion": 2510,
        "versionName": "20w09a"
    },
    {
        "dataVersion": 2512,
        "versionName": "20w10a"
    },
    {
        "dataVersion": 2513,
        "versionName": "20w11a"
    },
    {
        "dataVersion": 2515,
        "versionName": "20w12a"
    },
    {
        "dataVersion": 2520,
        "versionName": "20w13a"
    },
    {
        "dataVersion": 2521,
        "versionName": "20w13b"
    },
    {
        "dataVersion": 2524,
        "versionName": "20w14a"
    },
    {
        "dataVersion": 2525,
        "versionName": "20w15a"
    },
    {
        "dataVersion": 2526,
        "versionName": "20w16a"
    },
    {
        "dataVersion": 2529,
        "versionName": "20w17a"
    },
    {
        "dataVersion": 2532,
        "versionName": "20w18a"
    },
    {
        "dataVersion": 2534,
        "versionName": "20w19a"
    },
    {
        "dataVersion": 2536,
        "versionName": "20w20a"
    },
    {
        "dataVersion": 2537,
        "versionName": "20w20b"
    },
    {
        "dataVersion": 2555,
        "versionName": "20w22a"
    },
    {
        "dataVersion": 2556,
        "versionName": "1.16 Pre-release 1"
    },
    {
        "dataVersion": 2557,
        "versionName": "1.16 Pre-release 2"
    },
    {
        "dataVersion": 2559,
        "versionName": "1.16 Pre-release 3"
    },
    {
        "dataVersion": 2560,
        "versionName": "1.16 Pre-release 4"
    },
    {
        "dataVersion": 2561,
        "versionName": "1.16 Pre-release 5"
    },
    {
        "dataVersion": 2562,
        "versionName": "1.16 Pre-release 6"
    },
    {
        "dataVersion": 2563,
        "versionName": "1.16 Pre-release 7"
    },
    {
        "dataVersion": 2564,
        "versionName": "1.16 Pre-release 8"
    },
    {
        "dataVersion": 2565,
        "versionName": "1.16 Release Candidate 1"
    },
    {
        "dataVersion": 2566,
        "versionName": "1.16"
    },
    {
        "dataVersion": 2567,
        "versionName": "1.16.1"
    },
    {
        "dataVersion": 2569,
        "versionName": "20w27a"
    },
    {
        "dataVersion": 2570,
        "versionName": "20w28a"
    },
    {
        "dataVersion": 2571,
        "versionName": "20w29a"
    },
    {
        "dataVersion": 2572,
        "versionName": "20w30a"
    },
    {
        "dataVersion": 2573,
        "versionName": "1.16.2 Pre-release 1"
    },
    {
        "dataVersion": 2574,
        "versionName": "1.16.2 Pre-release 2"
    },
    {
        "dataVersion": 2575,
        "versionName": "1.16.2 Pre-release 3"
    },
    {
        "dataVersion": 2576,
        "versionName": "1.16.2 Release Candidate 1"
    },
    {
        "dataVersion": 2577,
        "versionName": "1.16.2 Release Candidate 2"
    },
    {
        "dataVersion": 2578,
        "versionName": "1.16.2"
    },
    {
        "dataVersion": 2579,
        "versionName": "1.16.3 Release Candidate 1"
    },
    {
        "dataVersion": 2580,
        "versionName": "1.16.3"
    },
    {
        "dataVersion": 2581,
        "versionName": "1.16.4 Pre-release 1"
    },
    {
        "dataVersion": 2582,
        "versionName": "1.16.4 Pre-release 2"
    },
    {
        "dataVersion": 2583,
        "versionName": "1.16.4 Release Candidate 1"
    },
    {
        "dataVersion": 2584,
        "versionName": "1.16.4"
    },
    {
        "dataVersion": 2585,
        "versionName": "1.16.5 Release Candidate 1"
    },
    {
        "dataVersion": 2586,
        "versionName": "1.16.5"
    },
    {
        "dataVersion": 2681,
        "versionName": "20w45a"
    },
    {
        "dataVersion": 2682,
        "versionName": "20w46a"
    },
    {
        "dataVersion": 2683,
        "versionName": "20w48a"
    },
    {
        "dataVersion": 2685,
        "versionName": "20w49a"
    },
    {
        "dataVersion": 2687,
        "versionName": "20w51a"
    },
    {
        "dataVersion": 2689,
        "versionName": "21w03a"
    },
    {
        "dataVersion": 2690,
        "versionName": "21w05a"
    },
    {
        "dataVersion": 2692,
        "versionName": "21w05b"
    },
    {
        "dataVersion": 2701,
        "versionName": "Combat Test 6"
    },
    {
        "dataVersion": 2704,
        "versionName": "Combat Test 7c"
    },
    {
        "dataVersion": 2706,
        "versionName": "Combat Test 8b"
    },
    {
        "dataVersion": 2707,
        "versionName": "Combat Test 8c"
    }
]
